{
  "schema_version": "0.1",
  "course_name": "国学大师",
  "skill_name": "国学大师",
  "roles": [
    "consultant"
  ],
  "modes": [
    "consultant"
  ],
  "scope": "single-course",
  "evidence_strategy": "standard",
  "progress_strategy": "none",
  "source_dir": "C:\\Users\\华硕\\Desktop\\daizhigev20-master\\daizhigev20-master",
  "generated_at": "2026-06-17T21:46:12",
  "generated_by": {
    "id": "lineage-skill",
    "repository": "https://github.com/JuneYaooo/lineage-skill",
    "script": "scripts/build_course_skill.py"
  },
  "provenance": {
    "watermark": "lineage-skill:course-skill-builder:v0.1",
    "watermark_visibility": "manifest-only",
    "source_package": "C:\\Users\\华硕\\Desktop\\daizhigev20-master\\daizhigev20-master\\course_package.json",
    "note": "This packaged course Skill was generated from course materials by lineage-skill."
  },
  "reference_status": {
    "course_package.json": "copied",
    "course_digest.md": "copied",
    "full_transcript.md": "stubbed",
    "concept_glossary.md": "derived",
    "quote_index.md": "stubbed",
    "study_paths.md": "derived",
    "lesson_index.json": "generated",
    "evidence_map.json": "generated",
    "consulting_playbook.md": "stubbed",
    "scenario_templates.md": "stubbed"
  }
}